{
  "settings": {
    "up_to_date": true
  },
  "deaths": [
    {
      "cause": "deathOnDuty",
      "count": 2,
      "published": true,
      "orphans": 1,
      "unpublished_reason": "",
      "year": "2021",
      "month": "01",
      "day": "02",
      "keywords": "Yvonne Huynh, Loïc Risser",
      "house": "armee",
      "peers": [],
      "text": "Deux militaires du 2eme RH sont décédés à bord de leur VBL d'une attaque par IED lors d'un opération de contrôle dans la région de Ménaka au Mali.",
      "section": "2eme RH",
      "location": "Région de Ménaka, Mali",
      "origin": "opex",
      "gps": {
        "accurate": false,
        "lat": 15.852774,
        "lon": 1.468974
      },
      "sources": [
        {
          "url": "https://twitter.com/CEMAT_FR/status/1345493205152919552",
          "titre": "@CEMAT_FR (Twitter)",
          "paywall": false
        },
        {
          "url": "https://www.defense.gouv.fr/terre/base/in-memoriam/mali/barkhane-deces-du-sergent-yvonne-huynh-et-du-brigadier-loic-risser-du-2e-regiment-de-hussards",
          "titre": "MINARM - Hommage",
          "paywall": false
        },
        {
          "url": "https://actu17.fr/mali-trois-militaires-francais-de-la-force-barkhane-tues-en-operation/",
          "titre": "Actu17",
          "paywall": false
        },
        {
          "url": "https://www.lemonde.fr/afrique/article/2021/01/02/deux-soldats-francais-tues-lors-d-une-operation-au-mali_6065052_3212.html",
          "titre": "Le Monde",
          "paywall": false
        },
        {
          "url": "https://www.francetvinfo.fr/monde/afrique/mali/guerre-au-mali/deux-soldats-francais-ont-ete-tues-au-mali-dans-l-explosion-de-leur-vehicule-annonce-l-elysee_4242293.html",
          "titre": "France Info",
          "paywall": false
        },
        {
          "url": "https://www.20minutes.fr/monde/2943687-20210103-mali-deux-soldats-francais-nouveau-tues-lors-operation",
          "titre": "20 minutes",
          "paywall": false
        }
      ]
    },
    {
      "cause": "suicide",
      "count": 1,
      "published": true,
      "orphans": 4,
      "unpublished_reason": "",
      "year": "2021",
      "month": "01",
      "day": "03",
      "keywords": "Etienne",
      "house": "police",
      "peers": [],
      "text": "Un policier de la PAF de Montgenèvre a mis fin à ses jours avec son arme de service dans son logement situé à Puy-Saint-Pierre (Hautes-Alpes).",
      "section": "DIDPAF 04-05",
      "location": "Montgenèvre (Hautes-Alpes)",
      "origin": "interieur",
      "gps": {
        "accurate": true,
        "lat": 44.93378570961448,
        "lon": 6.733964742339562
      },
      "sources": [
        {
          "url": "https://actu17.fr/hautes-alpes-un-policier-de-44-ans-se-suicide-avec-son-arme-de-service-a-son-domicile/",
          "titre": "Actu17",
          "paywall": false
        },
        {
          "url": "https://twitter.com/PoliceNat05/status/1346042597144489986",
          "titre": "@PoliceNat05 (Twitter)",
          "paywall": false
        },
        {
          "url": "https://www.ledauphine.com/faits-divers-justice/2021/01/04/hautes-alpes-un-fonctionnaire-de-la-police-aux-frontieres-met-fin-a-ses-jours",
          "titre": "Le Dauphiné",
          "paywall": false
        }
      ]
    },
    {
      "cause": "suicide",
      "count": 1,
      "published": true,
      "orphans": 2,
      "unpublished_reason": "",
      "year": "2021",
      "month": "01",
      "day": "08",
      "keywords": "Patrick Auguet",
      "house": "gendarmerie",
      "peers": [],
      "text": "Le major de Gendarmerie de la BMo de Toulouse a mis fin à ses jours avec son arme de service.\n Marié et père de deux filles il était l'adjoint au peloton motorisé de la BMo.",
      "section": "BMo (EDSR 31)",
      "location": "Toulouse (Haute-Garonne)",
      "origin": "interieur",
      "gps": {
        "accurate": true,
        "lat": 43.642956262499546,
        "lon": 1.4691198822913898
      },
      "sources": [
        {
          "url": "https://actu17.fr/deux-gendarmes-se-suicident-a-lyon-et-a-toulouse/",
          "titre": "Actu17",
          "paywall": false
        },
        {
          "url": "https://www.20minutes.fr/faits_divers/2949683-20210111-lyon-toulouse-sein-caserne-deux-gendarmes-suicident",
          "titre": "20 Minutes",
          "paywall": false
        },
        {
          "url": "https://lessor.org/articles-abonnes/encore-deux-suicides-dans-la-gendarmerie/",
          "titre": "L'Essor",
          "paywall": false
        },
        {
          "url": "https://www.midilibre.fr/2021/01/11/a-toulouse-et-a-lyon-deux-gendarmes-se-sont-suicides-9304534.php",
          "titre": "Midi Libre",
          "paywall": false
        },
        {
          "url": "https://www.lefigaro.fr/faits-divers/suicides-de-deux-gendarmes-a-lyon-et-a-toulouse-20210110",
          "titre": "Le Figaro",
          "paywall": false
        }
      ]
    },
    {
      "cause": "suicide",
      "count": 1,
      "published": true,
      "orphans": 1,
      "unpublished_reason": "",
      "year": "2021",
      "month": "01",
      "day": "08",
      "keywords": "Marie-Dominique Hoche",
      "house": "gendarmerie",
      "peers": [],
      "text": "Une gendarme de la caserne Général Guy-Delfosse à Lyon a mis fin à ses jours avec son arme de service.\n Elle était mère d'un enfant et cheffe de la BPDJ de Lyon.",
      "section": "BPDJ (GGD 69)",
      "location": "Lyon 2e (Rhône)",
      "origin": "interieur",
      "gps": {
        "accurate": true,
        "lat": 45.74717237193968,
        "lon": 4.8197460842699344
      },
      "sources": [
        {
          "url": "https://actu17.fr/deux-gendarmes-se-suicident-a-lyon-et-a-toulouse/",
          "titre": "Actu17",
          "paywall": false
        },
        {
          "url": "https://www.20minutes.fr/faits_divers/2949683-20210111-lyon-toulouse-sein-caserne-deux-gendarmes-suicident",
          "titre": "20 Minutes",
          "paywall": false
        },
        {
          "url": "https://lessor.org/articles-abonnes/encore-deux-suicides-dans-la-gendarmerie/",
          "titre": "L'Essor",
          "paywall": false
        },
        {
          "url": "https://www.midilibre.fr/2021/01/11/a-toulouse-et-a-lyon-deux-gendarmes-se-sont-suicides-9304534.php",
          "titre": "Midi Libre",
          "paywall": false
        },
        {
          "url": "https://www.lefigaro.fr/faits-divers/suicides-de-deux-gendarmes-a-lyon-et-a-toulouse-20210110",
          "titre": "Le Figaro",
          "paywall": false
        }
      ]
    },
    {
      "cause": "accident",
      "count": 1,
      "published": true,
      "orphans": 0,
      "unpublished_reason": "",
      "year": "2021",
      "month": "01",
      "day": "12",
      "keywords": "Jérémy Andrieux",
      "house": "gendarmerie",
      "peers": [],
      "text": "Un gendarme adjoint volontaire a perdu la vie dans un accident de la route en se rendant au CNEFG de Saint-Astier.",
      "section": "CNEFG Saint-Astier",
      "location": "Saint-Léon-sur-l’Isle (Dordogne)",
      "origin": "interieur",
      "gps": {
        "accurate": true,
        "lat": 45.09681606303209,
        "lon": 0.48014871954405725
      },
      "sources": [
        {
          "url": "https://france3-regions.francetvinfo.fr/nouvelle-aquitaine/dordogne/perigord/accident-mortel-st-leon-isle-24-1914064.html",
          "titre": "France Info",
          "paywall": false
        },
        {
          "url": "https://www.sudouest.fr/2021/01/12/dordogne-un-gendarme-meurt-dans-un-accident-de-la-route-8278238-1980.php",
          "titre": "Sud Ouest",
          "paywall": false
        },
        {
          "url": "https://actupenit.com/2021/01/12/dordogne-un-gendarme-du-cnefg-de-saint-astier-trouve-la-mort-ce-mardi-matin/",
          "titre": "Actupenit",
          "paywall": false
        }
      ]
    },
    {
      "cause": "deathOnDuty",
      "count": 1,
      "published": true,
      "orphans": 3,
      "unpublished_reason": "",
      "year": "2021",
      "month": "01",
      "day": "13",
      "keywords": "Laurent DELBREIL",
      "house": "pompier",
      "peers": [],
      "text": "Un pompier est décédé dans un grave accident de la circulation en se rendant sur une intervention.\n Marié et père de trois enfants, il était volontaire au CIS Mirecourt.",
      "section": "SDIS 88",
      "location": "Vroville (Vosges)",
      "origin": "interieur",
      "gps": {
        "accurate": false,
        "lat": 48.272076603832424,
        "lon": 6.156976913493413
      },
      "sources": [
        {
          "url": "https://twitter.com/PompiersFR/status/1349331420494311427",
          "titre": "@PompiersFR (Twitter)",
          "paywall": false
        },
        {
          "url": "https://actu17.fr/vosges-un-pompier-tue-dans-un-accident-de-la-route-en-allant-sur-une-intervention/",
          "titre": "Actu17",
          "paywall": false
        },
        {
          "url": "https://actu.fr/faits-divers/photo-un-pompier-tue-un-autre-gravement-blesse-dans-les-vosges-retour-sur-l-accident-ce-que-l-on-sait_38699463.html",
          "titre": "Actu.fr",
          "paywall": false
        },
        {
          "url": "https://france3-regions.francetvinfo.fr/grand-est/vosges/epinal/mirecourt-pompier-tue-autre-grievement-blesse-accident-camion-cause-du-verglas-1914540.html",
          "titre": "France Info",
          "paywall": false
        },
        {
          "url": "https://www.vosgesmatin.fr/faits-divers-justice/2021/01/13/pompier-decede-en-intervention-entre-mirecourt-et-dompaire-pluie-d-hommages",
          "titre": "Vosges Matin",
          "paywall": false
        },
        {
          "url": "https://www.gendinfo.fr/l-info-en-continu/vosges-un-sapeur-pompier-decede-et-un-second-grievement-blesse-dans-un-accident-de-la-circulation/",
          "titre": "Gend Info",
          "paywall": false
        }
      ]
    },
    {
      "cause": "deathOnDuty",
      "count": 1,
      "published": true,
      "orphans": 0,
      "unpublished_reason": "",
      "year": "2021",
      "month": "01",
      "day": "24",
      "keywords": "Jean-Paul ACCOLAS",
      "house": "pompier",
      "peers": [],
      "text": "Un pompier est décédé d'un arrêt cardiaque après son séance de sport pendant son service.\n Il était pompier volontaire depuis plus de 24 ans à la caserne de Givors.",
      "section": "SDIS 69",
      "location": "Givors (Rhône)",
      "origin": "interieur",
      "gps": {
        "accurate": false,
        "lat": 45.59904316839378,
        "lon": 4.767798465944594
      },
      "sources": [
        {
          "url": "https://twitter.com/SDMIS69/status/1353362150400602112",
          "titre": "@SDMIS69 (Twitter)",
          "paywall": false
        },
        {
          "url": "https://actupenit.com/2021/01/24/givors-un-sapeur-pompier-volontaire-retrouve-mort-a-la-caserne/",
          "titre": "Actupenit",
          "paywall": false
        },
        {
          "url": "https://www.leprogres.fr/faits-divers-justice/2021/01/24/un-pompier-volontaire-de-grigny-retrouve-mort-a-la-caserne-de-givors",
          "titre": "Le progrès",
          "paywall": false
        }
      ]
    },
    {
      "cause": "suicide",
      "count": 1,
      "published": true,
      "orphans": 2,
      "unpublished_reason": "",
      "year": "2021",
      "month": "01",
      "day": "25",
      "keywords": "Franck",
      "house": "police",
      "peers": [],
      "text": "Un policier de la CSP de Calais a mis fin a mis fin à ses jours avec son arme administrative à son domicile. \n Père de deux enfants il était en poste à Calais depuis une dizaine d'années.",
      "section": "CSP Calais",
      "location": "Zutkerque (Pas-de-Calais)",
      "origin": "interieur",
      "gps": {
        "accurate": true,
        "lat": 50.8524871734886,
        "lon": 2.063957540921227
      },
      "sources": [
        {
          "url": "https://actu17.fr/pas-de-calais-un-policier-sest-suicide-avec-son-arme-de-service-a-son-domicile/",
          "titre": "Actu17",
          "paywall": false
        },
        {
          "url": "https://twitter.com/PoliceNat62/status/1354016385668702208",
          "titre": "@PoliceNat62 (Twitter)",
          "paywall": false
        },
        {
          "url": "https://www.nordlittoral.fr/106006/article/2021-01-25/suicide-d-un-policier-de-calaisa-son-domicile-zutkerque",
          "titre": "Nord Littoral",
          "paywall": false
        },
        {
          "url": "https://www.lavoixdunord.fr/925302/article/2021-01-25/zutkerque-un-policier-de-calais-se-donne-la-mort-chez-lui-avec-son-arme-de",
          "titre": "La voix du Nord",
          "paywall": false
        }
      ]
    },
    {
      "cause": "deathOnDuty",
      "count": 1,
      "published": true,
      "orphans": 3,
      "unpublished_reason": "",
      "year": "2021",
      "month": "01",
      "day": "25",
      "keywords": "Naili MATAITAUA",
      "house": "pompier",
      "peers": [],
      "text": "Un pompier est décédé d'un arrêt cardiaque après son séance de sport pendant son service.\n Il était marié et père de trois enfants.",
      "section": "SDIS 987",
      "location": "Mahina (Polynésie Française)",
      "origin": "domtom",
      "gps": {
        "accurate": false,
        "lat": -17.507946694307048,
        "lon": -149.4813504466269
      },
      "sources": [
        {
          "url": "https://mobile.twitter.com/PompiersFR/status/1353789188622188551",
          "titre": "@PompiersFR (Twitter)",
          "paywall": false
        },
        {
          "url": "https://actupenit.com/2021/01/26/mahina-la-communaute-des-sapeurs-pompiers-dans-leffroi-apres-la-mort-subite-en-service-dun-des-leurs/",
          "titre": "Actupenit",
          "paywall": false
        }
      ]
    }
  ]
}
